Metadata-Version: 2.0
Name: odoo10-addon-printer-zpl2
Version: 10.0.1.1.2
Summary: Printer ZPL II
Home-page: http://www.syleam.fr/
Author: SYLEAM, Odoo Community Association (OCA)
Author-email: support@odoo-community.org
License: AGPL-3
Platform: UNKNOWN
Classifier: Programming Language :: Python
Classifier: Framework :: Odoo
Classifier: License :: OSI Approved :: GNU Affero General Public License v3
Requires-Python: ~=2.7
Requires-Dist: odoo (<10.1dev,>=10.0)
Requires-Dist: odoo10-addon-base-report-to-printer
Requires-Dist: zpl2
